Metadata-Version: 2.1
Name: vsh
Version: 0.7.2
Summary: Manager for python's virtual environments
